mtutils/__init__.py
mtutils/common_lib/__init__.py
mtutils/common_lib/demo.py
mtutils/common_lib/lib/__init__.py
mtutils/common_lib/lib/anno_manager.py
mtutils/common_lib/lib/data_manager.py
mtutils/common_lib/lib/evaluator.py
mtutils/common_lib/lib/labelme/__init__.py
mtutils/common_lib/lib/labelme/labelme.py
mtutils/common_lib/lib/labelme/main.py
mtutils/common_lib/lib/labelme/polygon.py
mtutils/common_lib/lib/utils/__init__.py
mtutils/common_lib/lib/utils/coding_related.py
mtutils/common_lib/lib/utils/id_related.py
mtutils/common_lib/lib/utils/mean_ap.py
mtutils/common_lib/lib/utils/path_related.py
mtutils/common_lib/lib/utils/classifier_eval/__init__.py
mtutils/common_lib/lib/utils/classifier_eval/eval_metrics.py
mtutils/common_lib/lib/utils/classifier_eval/example.py
mtutils/common_lib/lib/utils/classifier_eval/plot_confusion_matrix.py
mtutils/common_lib/lib/utils/classifier_eval/tmp_file.py
mtutils/common_lib/lib/utils/classifier_eval/utils.py
mtutils/utils_vvd/__init__.py
mtutils/utils_vvd/add_utils.py
mtutils/utils_vvd/array_processing.py
mtutils/utils_vvd/box_processing.py
mtutils/utils_vvd/circle_processing.py
mtutils/utils_vvd/image_processing.py
mtutils/utils_vvd/multi_processing.py
mtutils/utils_vvd/torch_utils.py
mtutils/utils_vvd/utils.py
mtutils-1.0.15.dist-info/METADATA
mtutils-1.0.15.dist-info/WHEEL
mtutils-1.0.15.dist-info/top_level.txt
mtutils-1.0.15.dist-info/RECORD
