Metadata-Version: 2.1
Name: mtutils
Version: 1.0.15
Summary: Commonly used function library by MT
Home-page: https://github.com/zywvvd/utils_vvd
Author: zywvvd
Author-email: zywvvd@mail.ustc.edu.cn
License: MIT
Platform: UNKNOWN
Requires-Dist: pypinyin
Requires-Dist: cv2
